abdm/__init__.py
abdm/api/__init__.py
abdm/api/consent_flow_api.py
abdm/api/data_flow_api.py
abdm/api/gateway_api.py
abdm/api/identification_api.py
abdm/api/monitoring_api.py
abdm/api/patient_notification_api.py
abdm/api/subscriptions_api.py
abdm/api/user_auth_api.py
abdm/api_client.py
abdm/api_response.py
abdm/configuration.py
abdm/exceptions.py
abdm/models/__init__.py
abdm/models/access_token_validity.py
abdm/models/auth_confirm_identifier.py
abdm/models/auth_confirm_identifier_type.py
abdm/models/auth_meta.py
abdm/models/authentication_mode.py
abdm/models/care_context_definition.py
abdm/models/certificate_or_key_get_schema.py
abdm/models/certs.py
abdm/models/consent.py
abdm/models/consent_acknowledgement.py
abdm/models/consent_artefact_reference.py
abdm/models/consent_artefact_response.py
abdm/models/consent_artefact_response_consent.py
abdm/models/consent_artefact_response_consent_consent_detail.py
abdm/models/consent_artefact_response_consent_consent_detail_care_contexts_inner.py
abdm/models/consent_artefact_response_consent_consent_detail_consent_manager.py
abdm/models/consent_artefact_response_consent_consent_detail_hip.py
abdm/models/consent_artefact_response_consent_consent_detail_hiu.py
abdm/models/consent_fetch_request.py
abdm/models/consent_manager_patient_id.py
abdm/models/consent_request.py
abdm/models/consent_request_consent.py
abdm/models/consent_request_consent_patient.py
abdm/models/consent_request_init_response.py
abdm/models/consent_request_init_response_consent_request.py
abdm/models/consent_request_status_request.py
abdm/models/consent_status.py
abdm/models/data_notification.py
abdm/models/data_notification_entries_inner.py
abdm/models/date_range.py
abdm/models/entry_content.py
abdm/models/entry_link.py
abdm/models/error.py
abdm/models/error_response.py
abdm/models/event_category_detail.py
abdm/models/health_information_notification.py
abdm/models/health_information_notification_notification.py
abdm-1.0.0.dist-info/LICENSE
abdm-1.0.0.dist-info/METADATA
abdm-1.0.0.dist-info/WHEEL
abdm-1.0.0.dist-info/RECORD
